etpy2png/__init__.py
etpy2png/conversions.py
etpy2png/driver/geckodriver.exe
etpy2png-0.0.10.dist-info/LICENSE
etpy2png-0.0.10.dist-info/METADATA
etpy2png-0.0.10.dist-info/WHEEL
etpy2png-0.0.10.dist-info/top_level.txt
etpy2png-0.0.10.dist-info/RECORD
