Metadata-Version: 2.1
Name: etpy2png
Version: 0.0.10
Summary: Converting .py Code-Files to .png with Code-Highlighting.
Author: ExperTeach GmbH
Author-email: et_dbu@web.de
License: UNKNOWN
Keywords: python,code,screenshot,png,py,code-highlighting
Platform: UNKNOWN
Classifier: Development Status :: 1 - Planning
Classifier: Intended Audience :: Developers
Classifier: Programming Language :: Python :: 3
Classifier: Operating System :: Microsoft :: Windows
License-File: LICENSE
Requires-Dist: selenium
Requires-Dist: nbconvert
